{
  "EUR_USD": {
    "symbol": "EUR_USD",
    "broker_symbol": "EURUSD",
    "direction": "bullish",
    "confluence": 15,
    "quality_factors": 5,
    "current_price": 1.17071,
    "entry": 1.16237914,
    "stop_loss": 1.1530668743126435,
    "tp1": 1.167966499412414,
    "tp2": 1.173553858824828,
    "tp3": 1.1810036713747132,
    "tp4": 1.1856598042183915,
    "tp5": 1.194972069905748,
    "entry_distance_r": 0.8946115026884175,
    "sl_pips": 931.2265687356546,
    "flags": {
      "htf_bias": true,
      "location": true,
      "fib": true,
      "liquidity": true,
      "structure": true,
      "confirmation": true,
      "rr": true,
      "atr_regime_ok": true,
      "pattern_confirmed": true,
      "zscore_valid": true,
      "mitigated_sr": true,
      "framework": true,
      "displacement": true,
      "rejection": true,
      "momentum": true
    },
    "notes": {
      "htf_bias": "HTF bias: B/B/B -> Bullish",
      "location": "Location filter disabled",
      "fib": "Fib filter disabled",
      "liquidity": "Liquidity filter removed",
      "structure": "Structure filter disabled",
      "confirmation": "Confirmation filter disabled",
      "rr": "R/R: Entry near 1.16238, SL at 1.15307",
      "atr_regime": "ATR regime filter disabled",
      "pattern": "Pattern filter disabled",
      "zscore": "Z-score filter disabled",
      "mitigated_sr": "Mitigated SR disabled",
      "framework": "Framework disabled",
      "displacement": "Displacement disabled",
      "rejection": "Candle rejection disabled",
      "momentum": "Momentum filter disabled"
    },
    "created_at": "2026-01-05T00:35:27.087377+00:00",
    "last_check": "2026-01-05T15:35:45.114251+00:00",
    "check_count": 422
  },
  "GBP_USD": {
    "symbol": "GBP_USD",
    "broker_symbol": "GBPUSD",
    "direction": "bullish",
    "confluence": 15,
    "quality_factors": 5,
    "current_price": 1.34416,
    "entry": 1.34414,
    "stop_loss": 1.3335559254783083,
    "tp1": 1.3504904447130148,
    "tp2": 1.3568408894260298,
    "tp3": 1.3653081490433832,
    "tp4": 1.370600186304229,
    "tp5": 1.3811842608259206,
    "entry_distance_r": 0.0018896314419500574,
    "sl_pips": 1058.4074521691632,
    "flags": {
      "htf_bias": true,
      "location": true,
      "fib": true,
      "liquidity": true,
      "structure": true,
      "confirmation": true,
      "rr": true,
      "atr_regime_ok": true,
      "pattern_confirmed": true,
      "zscore_valid": true,
      "mitigated_sr": true,
      "framework": true,
      "displacement": true,
      "rejection": true,
      "momentum": true
    },
    "notes": {
      "htf_bias": "HTF bias: B/M/B -> Bullish",
      "location": "Location filter disabled",
      "fib": "Fib filter disabled",
      "liquidity": "Liquidity filter removed",
      "structure": "Structure filter disabled",
      "confirmation": "Confirmation filter disabled",
      "rr": "R/R: Entry near 1.34414, SL at 1.33356",
      "atr_regime": "ATR regime filter disabled",
      "pattern": "Pattern filter disabled",
      "zscore": "Z-score filter disabled",
      "mitigated_sr": "Mitigated SR disabled",
      "framework": "Framework disabled",
      "displacement": "Displacement disabled",
      "rejection": "Candle rejection disabled",
      "momentum": "Momentum filter disabled"
    },
    "created_at": "2026-01-05T00:35:27.775898+00:00",
    "last_check": "2026-01-05T15:35:45.114251+00:00",
    "check_count": 422
  },
  "USD_JPY": {
    "symbol": "USD_JPY",
    "broker_symbol": "USDJPY",
    "direction": "bullish",
    "confluence": 15,
    "quality_factors": 5,
    "current_price": 157.145,
    "entry": 156.54863,
    "stop_loss": 155.3567353775129,
    "tp1": 157.26376677349225,
    "tp2": 157.97890354698453,
    "tp3": 158.9324192449742,
    "tp4": 159.52836655621775,
    "tp5": 160.72026117870485,
    "entry_distance_r": 0.5003546360126842,
    "sl_pips": 1191.8946224870979,
    "flags": {
      "htf_bias": true,
      "location": true,
      "fib": true,
      "liquidity": true,
      "structure": true,
      "confirmation": true,
      "rr": true,
      "atr_regime_ok": true,
      "pattern_confirmed": true,
      "zscore_valid": true,
      "mitigated_sr": true,
      "framework": true,
      "displacement": true,
      "rejection": true,
      "momentum": true
    },
    "notes": {
      "htf_bias": "HTF bias: B/B/B -> Bullish",
      "location": "Location filter disabled",
      "fib": "Fib filter disabled",
      "liquidity": "Liquidity filter removed",
      "structure": "Structure filter disabled",
      "confirmation": "Confirmation filter disabled",
      "rr": "R/R: Entry near 156.54863, SL at 155.35674",
      "atr_regime": "ATR regime filter disabled",
      "pattern": "Pattern filter disabled",
      "zscore": "Z-score filter disabled",
      "mitigated_sr": "Mitigated SR disabled",
      "framework": "Framework disabled",
      "displacement": "Displacement disabled",
      "rejection": "Candle rejection disabled",
      "momentum": "Momentum filter disabled"
    },
    "created_at": "2026-01-05T00:35:28.478960+00:00",
    "last_check": "2026-01-05T15:35:45.114251+00:00",
    "check_count": 422
  },
  "USD_CHF": {
    "symbol": "USD_CHF",
    "broker_symbol": "USDCHF",
    "direction": "bearish",
    "confluence": 15,
    "quality_factors": 5,
    "current_price": 0.79272,
    "entry": 0.7949037600000001,
    "stop_loss": 0.8017578131724615,
    "tp1": 0.7907913280965232,
    "tp2": 0.7866788961930463,
    "tp3": 0.7811956536550771,
    "tp4": 0.7777686270688464,
    "tp5": 0.770914573896385,
    "entry_distance_r": 0.31860855833072677,
    "sl_pips": 685.405317246146,
    "flags": {
      "htf_bias": true,
      "location": true,
      "fib": true,
      "liquidity": true,
      "structure": true,
      "confirmation": true,
      "rr": true,
      "atr_regime_ok": true,
      "pattern_confirmed": true,
      "zscore_valid": true,
      "mitigated_sr": true,
      "framework": true,
      "displacement": true,
      "rejection": true,
      "momentum": true
    },
    "notes": {
      "htf_bias": "HTF bias: B/B/B -> Bearish",
      "location": "Location filter disabled",
      "fib": "Fib filter disabled",
      "liquidity": "Liquidity filter removed",
      "structure": "Structure filter disabled",
      "confirmation": "Confirmation filter disabled",
      "rr": "R/R: Entry near 0.79490, SL at 0.80176",
      "atr_regime": "ATR regime filter disabled",
      "pattern": "Pattern filter disabled",
      "zscore": "Z-score filter disabled",
      "mitigated_sr": "Mitigated SR disabled",
      "framework": "Framework disabled",
      "displacement": "Displacement disabled",
      "rejection": "Candle rejection disabled",
      "momentum": "Momentum filter disabled"
    },
    "created_at": "2026-01-05T00:35:29.182312+00:00",
    "last_check": "2026-01-05T15:35:45.114251+00:00",
    "check_count": 422
  },
  "EUR_JPY": {
    "symbol": "EUR_JPY",
    "broker_symbol": "EURJPY",
    "direction": "bullish",
    "confluence": 15,
    "quality_factors": 5,
    "current_price": 183.971,
    "entry": 182.069738,
    "stop_loss": 180.00206215794702,
    "tp1": 183.3103435052318,
    "tp2": 184.55094901046357,
    "tp3": 186.20508968410596,
    "tp4": 187.23892760513246,
    "tp5": 189.3066034471854,
    "entry_distance_r": 0.9195164741646619,
    "sl_pips": 2067.6758420529777,
    "flags": {
      "htf_bias": true,
      "location": true,
      "fib": true,
      "liquidity": true,
      "structure": true,
      "confirmation": true,
      "rr": true,
      "atr_regime_ok": true,
      "pattern_confirmed": true,
      "zscore_valid": true,
      "mitigated_sr": true,
      "framework": true,
      "displacement": true,
      "rejection": true,
      "momentum": true
    },
    "notes": {
      "htf_bias": "HTF bias: B/B/B -> Bullish",
      "location": "Location filter disabled",
      "fib": "Fib filter disabled",
      "liquidity": "Liquidity filter removed",
      "structure": "Structure filter disabled",
      "confirmation": "Confirmation filter disabled",
      "rr": "R/R: Entry near 182.06974, SL at 180.00206",
      "atr_regime": "ATR regime filter disabled",
      "pattern": "Pattern filter disabled",
      "zscore": "Z-score filter disabled",
      "mitigated_sr": "Mitigated SR disabled",
      "framework": "Framework disabled",
      "displacement": "Displacement disabled",
      "rejection": "Candle rejection disabled",
      "momentum": "Momentum filter disabled"
    },
    "created_at": "2026-01-05T00:35:32.859294+00:00",
    "last_check": "2026-01-05T15:35:45.114251+00:00",
    "check_count": 422
  },
  "EUR_NZD": {
    "symbol": "EUR_NZD",
    "broker_symbol": "EURNZD",
    "direction": "bullish",
    "confluence": 15,
    "quality_factors": 5,
    "current_price": 2.03301,
    "entry": 2.0257695,
    "stop_loss": 2.0116066524398186,
    "tp1": 2.0342672085361087,
    "tp2": 2.0427649170722177,
    "tp3": 2.0540951951203628,
    "tp4": 2.0611766189004532,
    "tp5": 2.075339466460635,
    "entry_distance_r": 0.5112319375911758,
    "sl_pips": 1416.2847560181378,
    "flags": {
      "htf_bias": true,
      "location": true,
      "fib": true,
      "liquidity": true,
      "structure": true,
      "confirmation": true,
      "rr": true,
      "atr_regime_ok": true,
      "pattern_confirmed": true,
      "zscore_valid": true,
      "mitigated_sr": true,
      "framework": true,
      "displacement": true,
      "rejection": true,
      "momentum": true
    },
    "notes": {
      "htf_bias": "HTF bias: B/B/B -> Bullish",
      "location": "Location filter disabled",
      "fib": "Fib filter disabled",
      "liquidity": "Liquidity filter removed",
      "structure": "Structure filter disabled",
      "confirmation": "Confirmation filter disabled",
      "rr": "R/R: Entry near 2.02577, SL at 2.01161",
      "atr_regime": "ATR regime filter disabled",
      "pattern": "Pattern filter disabled",
      "zscore": "Z-score filter disabled",
      "mitigated_sr": "Mitigated SR disabled",
      "framework": "Framework disabled",
      "displacement": "Displacement disabled",
      "rejection": "Candle rejection disabled",
      "momentum": "Momentum filter disabled"
    },
    "created_at": "2026-01-05T00:35:35.663600+00:00",
    "last_check": "2026-01-05T15:35:45.114251+00:00",
    "check_count": 422
  },
  "GBP_CHF": {
    "symbol": "GBP_CHF",
    "broker_symbol": "GBPCHF",
    "direction": "bearish",
    "confluence": 15,
    "quality_factors": 5,
    "current_price": 1.06565,
    "entry": 1.0700685600000002,
    "stop_loss": 1.0767240952770412,
    "tp1": 1.0660752388337755,
    "tp2": 1.062081917667551,
    "tp3": 1.0567574894459182,
    "tp4": 1.0534297218073978,
    "tp5": 1.0467741865303566,
    "entry_distance_r": 0.6638925069246491,
    "sl_pips": 665.5535277040991,
    "flags": {
      "htf_bias": true,
      "location": true,
      "fib": true,
      "liquidity": true,
      "structure": true,
      "confirmation": true,
      "rr": true,
      "atr_regime_ok": true,
      "pattern_confirmed": true,
      "zscore_valid": true,
      "mitigated_sr": true,
      "framework": true,
      "displacement": true,
      "rejection": true,
      "momentum": true
    },
    "notes": {
      "htf_bias": "HTF bias: B/B/B -> Bearish",
      "location": "Location filter disabled",
      "fib": "Fib filter disabled",
      "liquidity": "Liquidity filter removed",
      "structure": "Structure filter disabled",
      "confirmation": "Confirmation filter disabled",
      "rr": "R/R: Entry near 1.07007, SL at 1.07672",
      "atr_regime": "ATR regime filter disabled",
      "pattern": "Pattern filter disabled",
      "zscore": "Z-score filter disabled",
      "mitigated_sr": "Mitigated SR disabled",
      "framework": "Framework disabled",
      "displacement": "Displacement disabled",
      "rejection": "Candle rejection disabled",
      "momentum": "Momentum filter disabled"
    },
    "created_at": "2026-01-05T00:35:37.085422+00:00",
    "last_check": "2026-01-05T15:35:45.114251+00:00",
    "check_count": 422
  },
  "GBP_AUD": {
    "symbol": "GBP_AUD",
    "broker_symbol": "GBPAUD",
    "direction": "bearish",
    "confluence": 15,
    "quality_factors": 5,
    "current_price": 2.01197,
    "entry": 2.01769378,
    "stop_loss": 2.0280110278984655,
    "tp1": 2.011503431260921,
    "tp2": 2.0053130825218415,
    "tp3": 1.9970592842030692,
    "tp4": 1.9919006602538365,
    "tp5": 1.981583412355371,
    "entry_distance_r": 0.5547777911638265,
    "sl_pips": 1031.7247898465441,
    "flags": {
      "htf_bias": true,
      "location": true,
      "fib": true,
      "liquidity": true,
      "structure": true,
      "confirmation": true,
      "rr": true,
      "atr_regime_ok": true,
      "pattern_confirmed": true,
      "zscore_valid": true,
      "mitigated_sr": true,
      "framework": true,
      "displacement": true,
      "rejection": true,
      "momentum": true
    },
    "notes": {
      "htf_bias": "HTF bias: B/B/B -> Bearish",
      "location": "Location filter disabled",
      "fib": "Fib filter disabled",
      "liquidity": "Liquidity filter removed",
      "structure": "Structure filter disabled",
      "confirmation": "Confirmation filter disabled",
      "rr": "R/R: Entry near 2.01769, SL at 2.02801",
      "atr_regime": "ATR regime filter disabled",
      "pattern": "Pattern filter disabled",
      "zscore": "Z-score filter disabled",
      "mitigated_sr": "Mitigated SR disabled",
      "framework": "Framework disabled",
      "displacement": "Displacement disabled",
      "rejection": "Candle rejection disabled",
      "momentum": "Momentum filter disabled"
    },
    "created_at": "2026-01-05T00:35:37.788697+00:00",
    "last_check": "2026-01-05T15:35:45.114251+00:00",
    "check_count": 422
  },
  "GBP_CAD": {
    "symbol": "GBP_CAD",
    "broker_symbol": "GBPCAD",
    "direction": "bullish",
    "confluence": 15,
    "quality_factors": 5,
    "current_price": 1.84749,
    "entry": 1.85133186,
    "stop_loss": 1.8347762585917862,
    "tp1": 1.8612652208449283,
    "tp2": 1.8711985816898564,
    "tp3": 1.8844430628164275,
    "tp4": 1.8927208635205344,
    "tp5": 1.9092764649287481,
    "entry_distance_r": 0.2320580150047459,
    "sl_pips": 1655.560140821377,
    "flags": {
      "htf_bias": true,
      "location": true,
      "fib": true,
      "liquidity": true,
      "structure": true,
      "confirmation": true,
      "rr": true,
      "atr_regime_ok": true,
      "pattern_confirmed": true,
      "zscore_valid": true,
      "mitigated_sr": true,
      "framework": true,
      "displacement": true,
      "rejection": true,
      "momentum": true
    },
    "notes": {
      "htf_bias": "HTF bias: B/B/B -> Bullish",
      "location": "Location filter disabled",
      "fib": "Fib filter disabled",
      "liquidity": "Liquidity filter removed",
      "structure": "Structure filter disabled",
      "confirmation": "Confirmation filter disabled",
      "rr": "R/R: Entry near 1.85133, SL at 1.83478",
      "atr_regime": "ATR regime filter disabled",
      "pattern": "Pattern filter disabled",
      "zscore": "Z-score filter disabled",
      "mitigated_sr": "Mitigated SR disabled",
      "framework": "Framework disabled",
      "displacement": "Displacement disabled",
      "rejection": "Candle rejection disabled",
      "momentum": "Momentum filter disabled"
    },
    "created_at": "2026-01-05T00:35:38.491664+00:00",
    "last_check": "2026-01-05T15:35:45.114251+00:00",
    "check_count": 422
  },
  "NZD_JPY": {
    "symbol": "NZD_JPY",
    "broker_symbol": "NZDJPY",
    "direction": "bullish",
    "confluence": 15,
    "quality_factors": 5,
    "current_price": 90.468,
    "entry": 90.063184,
    "stop_loss": 89.03767756663741,
    "tp1": 90.67848786001757,
    "tp2": 91.29379172003512,
    "tp3": 92.1141968667252,
    "tp4": 92.62695008340648,
    "tp5": 93.65245651676909,
    "entry_distance_r": 0.3947474017033921,
    "sl_pips": 1025.5064333625937,
    "flags": {
      "htf_bias": true,
      "location": true,
      "fib": true,
      "liquidity": true,
      "structure": true,
      "confirmation": true,
      "rr": true,
      "atr_regime_ok": true,
      "pattern_confirmed": true,
      "zscore_valid": true,
      "mitigated_sr": true,
      "framework": true,
      "displacement": true,
      "rejection": true,
      "momentum": true
    },
    "notes": {
      "htf_bias": "HTF bias: B/B/B -> Bullish",
      "location": "Location filter disabled",
      "fib": "Fib filter disabled",
      "liquidity": "Liquidity filter removed",
      "structure": "Structure filter disabled",
      "confirmation": "Confirmation filter disabled",
      "rr": "R/R: Entry near 90.06318, SL at 89.03768",
      "atr_regime": "ATR regime filter disabled",
      "pattern": "Pattern filter disabled",
      "zscore": "Z-score filter disabled",
      "mitigated_sr": "Mitigated SR disabled",
      "framework": "Framework disabled",
      "displacement": "Displacement disabled",
      "rejection": "Candle rejection disabled",
      "momentum": "Momentum filter disabled"
    },
    "created_at": "2026-01-05T00:35:42.741744+00:00",
    "last_check": "2026-01-05T15:35:45.114251+00:00",
    "check_count": 422
  },
  "NZD_CHF": {
    "symbol": "NZD_CHF",
    "broker_symbol": "NZDCHF",
    "direction": "bearish",
    "confluence": 15,
    "quality_factors": 5,
    "current_price": 0.45654,
    "entry": 0.45917576,
    "stop_loss": 0.46911648030334185,
    "tp1": 0.4532113278179949,
    "tp2": 0.44724689563598974,
    "tp3": 0.43929431939331626,
    "tp4": 0.43432395924164535,
    "tp5": 0.42438323893830343,
    "entry_distance_r": 0.2651477880444839,
    "sl_pips": 994.0720303341865,
    "flags": {
      "htf_bias": true,
      "location": true,
      "fib": true,
      "liquidity": true,
      "structure": true,
      "confirmation": true,
      "rr": true,
      "atr_regime_ok": true,
      "pattern_confirmed": true,
      "zscore_valid": true,
      "mitigated_sr": true,
      "framework": true,
      "displacement": true,
      "rejection": true,
      "momentum": true
    },
    "notes": {
      "htf_bias": "HTF bias: B/B/B -> Bearish",
      "location": "Location filter disabled",
      "fib": "Fib filter disabled",
      "liquidity": "Liquidity filter removed",
      "structure": "Structure filter disabled",
      "confirmation": "Confirmation filter disabled",
      "rr": "R/R: Entry near 0.45918, SL at 0.46912",
      "atr_regime": "ATR regime filter disabled",
      "pattern": "Pattern filter disabled",
      "zscore": "Z-score filter disabled",
      "mitigated_sr": "Mitigated SR disabled",
      "framework": "Framework disabled",
      "displacement": "Displacement disabled",
      "rejection": "Candle rejection disabled",
      "momentum": "Momentum filter disabled"
    },
    "created_at": "2026-01-05T00:35:43.460447+00:00",
    "last_check": "2026-01-05T15:35:45.114251+00:00",
    "check_count": 422
  },
  "NZD_CAD": {
    "symbol": "NZD_CAD",
    "broker_symbol": "NZDCAD",
    "direction": "bearish",
    "confluence": 15,
    "quality_factors": 5,
    "current_price": 0.7916,
    "entry": 0.796048,
    "stop_loss": 0.8026368300152065,
    "tp1": 0.7920947019908761,
    "tp2": 0.7881414039817521,
    "tp3": 0.782870339969587,
    "tp4": 0.7795759249619838,
    "tp5": 0.7729870949467772,
    "entry_distance_r": 0.6750819173866042,
    "sl_pips": 658.8830015206493,
    "flags": {
      "htf_bias": true,
      "location": true,
      "fib": true,
      "liquidity": true,
      "structure": true,
      "confirmation": true,
      "rr": true,
      "atr_regime_ok": true,
      "pattern_confirmed": true,
      "zscore_valid": true,
      "mitigated_sr": true,
      "framework": true,
      "displacement": true,
      "rejection": true,
      "momentum": true
    },
    "notes": {
      "htf_bias": "HTF bias: B/B/B -> Bearish",
      "location": "Location filter disabled",
      "fib": "Fib filter disabled",
      "liquidity": "Liquidity filter removed",
      "structure": "Structure filter disabled",
      "confirmation": "Confirmation filter disabled",
      "rr": "R/R: Entry near 0.79605, SL at 0.80264",
      "atr_regime": "ATR regime filter disabled",
      "pattern": "Pattern filter disabled",
      "zscore": "Z-score filter disabled",
      "mitigated_sr": "Mitigated SR disabled",
      "framework": "Framework disabled",
      "displacement": "Displacement disabled",
      "rejection": "Candle rejection disabled",
      "momentum": "Momentum filter disabled"
    },
    "created_at": "2026-01-05T00:35:44.180794+00:00",
    "last_check": "2026-01-05T15:35:45.114251+00:00",
    "check_count": 422
  },
  "CAD_JPY": {
    "symbol": "CAD_JPY",
    "broker_symbol": "CADJPY",
    "direction": "bullish",
    "confluence": 15,
    "quality_factors": 5,
    "current_price": 114.322,
    "entry": 113.494638,
    "stop_loss": 112.53427627511137,
    "tp1": 114.07085503493317,
    "tp2": 114.64707206986635,
    "tp3": 115.41536144977725,
    "tp4": 115.89554231222156,
    "tp5": 116.8559040371102,
    "entry_distance_r": 0.8615108021885776,
    "sl_pips": 960.361724888628,
    "flags": {
      "htf_bias": true,
      "location": true,
      "fib": true,
      "liquidity": true,
      "structure": true,
      "confirmation": true,
      "rr": true,
      "atr_regime_ok": true,
      "pattern_confirmed": true,
      "zscore_valid": true,
      "mitigated_sr": true,
      "framework": true,
      "displacement": true,
      "rejection": true,
      "momentum": true
    },
    "notes": {
      "htf_bias": "HTF bias: B/B/B -> Bullish",
      "location": "Location filter disabled",
      "fib": "Fib filter disabled",
      "liquidity": "Liquidity filter removed",
      "structure": "Structure filter disabled",
      "confirmation": "Confirmation filter disabled",
      "rr": "R/R: Entry near 113.49464, SL at 112.53428",
      "atr_regime": "ATR regime filter disabled",
      "pattern": "Pattern filter disabled",
      "zscore": "Z-score filter disabled",
      "mitigated_sr": "Mitigated SR disabled",
      "framework": "Framework disabled",
      "displacement": "Displacement disabled",
      "rejection": "Candle rejection disabled",
      "momentum": "Momentum filter disabled"
    },
    "created_at": "2026-01-05T00:35:44.882291+00:00",
    "last_check": "2026-01-05T15:35:45.114251+00:00",
    "check_count": 422
  },
  "CAD_CHF": {
    "symbol": "CAD_CHF",
    "broker_symbol": "CADCHF",
    "direction": "bearish",
    "confluence": 15,
    "quality_factors": 5,
    "current_price": 0.5768,
    "entry": 0.57989702,
    "stop_loss": 0.5861623683519755,
    "tp1": 0.5761378109888147,
    "tp2": 0.5723786019776294,
    "tp3": 0.5673663232960489,
    "tp4": 0.564233649120061,
    "tp5": 0.5579683007680856,
    "entry_distance_r": 0.4943093066841952,
    "sl_pips": 626.5348351975563,
    "flags": {
      "htf_bias": true,
      "location": true,
      "fib": true,
      "liquidity": true,
      "structure": true,
      "confirmation": true,
      "rr": true,
      "atr_regime_ok": true,
      "pattern_confirmed": true,
      "zscore_valid": true,
      "mitigated_sr": true,
      "framework": true,
      "displacement": true,
      "rejection": true,
      "momentum": true
    },
    "notes": {
      "htf_bias": "HTF bias: B/B/B -> Bearish",
      "location": "Location filter disabled",
      "fib": "Fib filter disabled",
      "liquidity": "Liquidity filter removed",
      "structure": "Structure filter disabled",
      "confirmation": "Confirmation filter disabled",
      "rr": "R/R: Entry near 0.57990, SL at 0.58616",
      "atr_regime": "ATR regime filter disabled",
      "pattern": "Pattern filter disabled",
      "zscore": "Z-score filter disabled",
      "mitigated_sr": "Mitigated SR disabled",
      "framework": "Framework disabled",
      "displacement": "Displacement disabled",
      "rejection": "Candle rejection disabled",
      "momentum": "Momentum filter disabled"
    },
    "created_at": "2026-01-05T00:35:45.569858+00:00",
    "last_check": "2026-01-05T15:35:45.114251+00:00",
    "check_count": 422
  },
  "XAU_USD": {
    "symbol": "XAU_USD",
    "broker_symbol": "XAUUSD",
    "direction": "bullish",
    "confluence": 15,
    "quality_factors": 5,
    "current_price": 4388.94,
    "entry": 4388.66,
    "stop_loss": 4240.344986204245,
    "tp1": 4477.649008277453,
    "tp2": 4566.638016554905,
    "tp3": 4685.290027591509,
    "tp4": 4759.447534489386,
    "tp5": 4907.762548285141,
    "entry_distance_r": 0.0018878736065475806,
    "sl_pips": 14831.501379575457,
    "flags": {
      "htf_bias": true,
      "location": true,
      "fib": true,
      "liquidity": true,
      "structure": true,
      "confirmation": true,
      "rr": true,
      "atr_regime_ok": true,
      "pattern_confirmed": true,
      "zscore_valid": true,
      "mitigated_sr": true,
      "framework": true,
      "displacement": true,
      "rejection": true,
      "momentum": true
    },
    "notes": {
      "htf_bias": "HTF bias: B/B/B -> Bullish",
      "location": "Location filter disabled",
      "fib": "Fib filter disabled",
      "liquidity": "Liquidity filter removed",
      "structure": "Structure filter disabled",
      "confirmation": "Confirmation filter disabled",
      "rr": "R/R: Entry near 4388.66000, SL at 4240.34499",
      "atr_regime": "ATR regime filter disabled",
      "pattern": "Pattern filter disabled",
      "zscore": "Z-score filter disabled",
      "mitigated_sr": "Mitigated SR disabled",
      "framework": "Framework disabled",
      "displacement": "Displacement disabled",
      "rejection": "Candle rejection disabled",
      "momentum": "Momentum filter disabled"
    },
    "created_at": "2026-01-05T00:35:46.976573+00:00",
    "last_check": "2026-01-05T15:35:45.114251+00:00",
    "check_count": 53
  },
  "XAG_USD": {
    "symbol": "XAG_USD",
    "broker_symbol": "XAGUSD",
    "direction": "bullish",
    "confluence": 15,
    "quality_factors": 5,
    "current_price": 75.139,
    "entry": 68.412402,
    "stop_loss": 59.78738930190337,
    "tp1": 73.58740961885798,
    "tp2": 78.76241723771597,
    "tp3": 85.66242739619327,
    "tp4": 89.97493374524159,
    "tp5": 98.59994644333821,
    "entry_distance_r": 0.7798942720959032,
    "sl_pips": 8625.012698096632,
    "flags": {
      "htf_bias": true,
      "location": true,
      "fib": true,
      "liquidity": true,
      "structure": true,
      "confirmation": true,
      "rr": true,
      "atr_regime_ok": true,
      "pattern_confirmed": true,
      "zscore_valid": true,
      "mitigated_sr": true,
      "framework": true,
      "displacement": true,
      "rejection": true,
      "momentum": true
    },
    "notes": {
      "htf_bias": "HTF bias: B/B/B -> Bullish",
      "location": "Location filter disabled",
      "fib": "Fib filter disabled",
      "liquidity": "Liquidity filter removed",
      "structure": "Structure filter disabled",
      "confirmation": "Confirmation filter disabled",
      "rr": "R/R: Entry near 68.41240, SL at 59.78739",
      "atr_regime": "ATR regime filter disabled",
      "pattern": "Pattern filter disabled",
      "zscore": "Z-score filter disabled",
      "mitigated_sr": "Mitigated SR disabled",
      "framework": "Framework disabled",
      "displacement": "Displacement disabled",
      "rejection": "Candle rejection disabled",
      "momentum": "Momentum filter disabled"
    },
    "created_at": "2026-01-05T00:35:47.710543+00:00",
    "last_check": "2026-01-05T15:35:45.114251+00:00",
    "check_count": 53
  }
}